envoy_schema/__init__.py
envoy_schema/py.typed
envoy_schema/admin/__init__.py
envoy_schema/admin/schema/__init__.py
envoy_schema/admin/schema/aggregator.py
envoy_schema/admin/schema/archive.py
envoy_schema/admin/schema/base.py
envoy_schema/admin/schema/billing.py
envoy_schema/admin/schema/certificate.py
envoy_schema/admin/schema/config.py
envoy_schema/admin/schema/doe.py
envoy_schema/admin/schema/log.py
envoy_schema/admin/schema/pricing.py
envoy_schema/admin/schema/site.py
envoy_schema/admin/schema/site_control.py
envoy_schema/admin/schema/site_group.py
envoy_schema/admin/schema/site_reading.py
envoy_schema/admin/schema/uri.py
envoy_schema/server/__init__.py
envoy_schema/server/schema/__init__.py
envoy_schema/server/schema/uri.py
envoy_schema/server/schema/csip_aus/__init__.py
envoy_schema/server/schema/csip_aus/connection_point.py
envoy_schema/server/schema/sep2/__init__.py
envoy_schema/server/schema/sep2/base.py
envoy_schema/server/schema/sep2/der.py
envoy_schema/server/schema/sep2/der_control_types.py
envoy_schema/server/schema/sep2/device_capability.py
envoy_schema/server/schema/sep2/end_device.py
envoy_schema/server/schema/sep2/error.py
envoy_schema/server/schema/sep2/event.py
envoy_schema/server/schema/sep2/function_set_assignments.py
envoy_schema/server/schema/sep2/identification.py
envoy_schema/server/schema/sep2/log_events.py
envoy_schema/server/schema/sep2/metering.py
envoy_schema/server/schema/sep2/metering_mirror.py
envoy_schema/server/schema/sep2/pricing.py
envoy_schema/server/schema/sep2/primitive_types.py
envoy_schema/server/schema/sep2/pub_sub.py
envoy_schema/server/schema/sep2/response.py
envoy_schema/server/schema/sep2/time.py
envoy_schema/server/schema/sep2/types.py
envoy_schema-0.31.0.dist-info/licenses/LICENSE.txt
envoy_schema-0.31.0.dist-info/METADATA
envoy_schema-0.31.0.dist-info/WHEEL
envoy_schema-0.31.0.dist-info/top_level.txt
envoy_schema-0.31.0.dist-info/RECORD
