Metadata-Version: 2.4
Name: envoy_schema
Version: 0.31.0
Summary: Envoy Schema - a collection of pydantic models compatible with the Envoy utility server
Author: Battery Storage and Grid Integration Program
Project-URL: Homepage, https://github.com/bsgip/envoy-schema
Keywords: envoy,csip-aus,2030.5,csip,pydantic
Classifier: Development Status :: 4 - Beta
Classifier: Intended Audience :: Developers
Classifier: Topic :: Software Development :: Testing
Classifier: Framework :: Pydantic
Classifier: License :: OSI Approved :: MIT License
Classifier: Programming Language :: Python :: 3
Classifier: Programming Language :: Python :: 3.9
Classifier: Programming Language :: Python :: 3.10
Classifier: Programming Language :: Python :: 3.11
Requires-Python: >=3.9
License-File: LICENSE.txt
Requires-Dist: pydantic!=2.17.1,!=2.6.0,>=2.5.0
Requires-Dist: pydantic_xml[lxml]>=2.12.0
Provides-Extra: all
Requires-Dist: envoy_schema[dev,test]; extra == "all"
Provides-Extra: dev
Requires-Dist: bandit; extra == "dev"
Requires-Dist: flake8; extra == "dev"
Requires-Dist: mypy; extra == "dev"
Requires-Dist: types-python-dateutil; extra == "dev"
Requires-Dist: types-tzlocal; extra == "dev"
Provides-Extra: test
Requires-Dist: pytest; extra == "test"
Requires-Dist: assertical; extra == "test"
Dynamic: license-file
